odoo/addons/stock_orderpoint_uom/README.rst
odoo/addons/stock_orderpoint_uom/__init__.py
odoo/addons/stock_orderpoint_uom/__manifest__.py
odoo/addons/stock_orderpoint_uom/i18n/ca.po
odoo/addons/stock_orderpoint_uom/i18n/de.po
odoo/addons/stock_orderpoint_uom/i18n/es.po
odoo/addons/stock_orderpoint_uom/i18n/es_ES.po
odoo/addons/stock_orderpoint_uom/i18n/es_MX.po
odoo/addons/stock_orderpoint_uom/i18n/fi.po
odoo/addons/stock_orderpoint_uom/i18n/fr.po
odoo/addons/stock_orderpoint_uom/i18n/fr_CH.po
odoo/addons/stock_orderpoint_uom/i18n/hr.po
odoo/addons/stock_orderpoint_uom/i18n/hr_HR.po
odoo/addons/stock_orderpoint_uom/i18n/it.po
odoo/addons/stock_orderpoint_uom/i18n/nl.po
odoo/addons/stock_orderpoint_uom/i18n/nl_NL.po
odoo/addons/stock_orderpoint_uom/i18n/pt_BR.po
odoo/addons/stock_orderpoint_uom/i18n/pt_PT.po
odoo/addons/stock_orderpoint_uom/i18n/ro.po
odoo/addons/stock_orderpoint_uom/i18n/sl.po
odoo/addons/stock_orderpoint_uom/i18n/stock_orderpoint_uom.pot
odoo/addons/stock_orderpoint_uom/i18n/tr.po
odoo/addons/stock_orderpoint_uom/i18n/tr_TR.po
odoo/addons/stock_orderpoint_uom/i18n/vi_VN.po
odoo/addons/stock_orderpoint_uom/i18n/zh_CN.po
odoo/addons/stock_orderpoint_uom/models/__init__.py
odoo/addons/stock_orderpoint_uom/models/procurement_group.py
odoo/addons/stock_orderpoint_uom/models/product_template.py
odoo/addons/stock_orderpoint_uom/models/stock_warehouse_orderpoint.py
odoo/addons/stock_orderpoint_uom/readme/CONFIGURE.md
odoo/addons/stock_orderpoint_uom/readme/CONTRIBUTORS.md
odoo/addons/stock_orderpoint_uom/readme/DESCRIPTION.md
odoo/addons/stock_orderpoint_uom/readme/USAGE.md
odoo/addons/stock_orderpoint_uom/static/description/icon.png
odoo/addons/stock_orderpoint_uom/static/description/index.html
odoo/addons/stock_orderpoint_uom/tests/__init__.py
odoo/addons/stock_orderpoint_uom/tests/test_stock_orderpoint_procure_uom.py
odoo/addons/stock_orderpoint_uom/views/stock_warehouse_orderpoint_view.xml
odoo_addon_stock_orderpoint_uom-18.0.1.0.0.2.dist-info/METADATA
odoo_addon_stock_orderpoint_uom-18.0.1.0.0.2.dist-info/WHEEL
odoo_addon_stock_orderpoint_uom-18.0.1.0.0.2.dist-info/top_level.txt
odoo_addon_stock_orderpoint_uom-18.0.1.0.0.2.dist-info/RECORD
