Metadata-Version: 2.1
Name: odoo-addon-stock_orderpoint_uom
Version: 18.0.1.0.0.2
Requires-Python: >=3.10
Requires-Dist: odoo==18.0.*
Summary: Allows to create procurement orders in the UoM indicated in the orderpoint
Home-page: https://github.com/OCA/stock-logistics-orderpoint
License: AGPL-3
Author: ForgeFlow, Odoo Community Association (OCA)
Author-email: support@odoo-community.org
Classifier: Programming Language :: Python
Classifier: Framework :: Odoo
Classifier: Framework :: Odoo :: 18.0
Classifier: License :: OSI Approved :: GNU Affero General Public License v3
